monk/__init__.py
monk/compare_prototype.py
monk/gluon_prototype.py
monk/gluon_tests.py
monk/keras_prototype.py
monk/keras_tests.py
monk/pytorch_prototype.py
monk/pytorch_tests.py
monk/gluon/__init__.py
monk/gluon/datasets/__init__.py
monk/gluon/datasets/class_imbalance.py
monk/gluon/datasets/csv_dataset.py
monk/gluon/datasets/imports.py
monk/gluon/datasets/params.py
monk/gluon/datasets/paths.py
monk/gluon/finetune/__init__.py
monk/gluon/finetune/imports.py
monk/gluon/finetune/level_10_schedulers_main.py
monk/gluon/finetune/level_11_optimizers_main.py
monk/gluon/finetune/level_12_losses_main.py
monk/gluon/finetune/level_13_updates_main.py
monk/gluon/finetune/level_14_master_main.py
monk/gluon/finetune/level_1_dataset_base.py
monk/gluon/finetune/level_2_model_base.py
monk/gluon/finetune/level_3_training_base.py
monk/gluon/finetune/level_4_evaluation_base.py
monk/gluon/finetune/level_5_state_base.py
monk/gluon/finetune/level_6_params_main.py
monk/gluon/finetune/level_7_aux_main.py
monk/gluon/finetune/level_8_layers_main.py
monk/gluon/finetune/level_9_transforms_main.py
monk/gluon/losses/__init__.py
monk/gluon/losses/imports.py
monk/gluon/losses/losses.py
monk/gluon/losses/retrieve_loss.py
monk/gluon/losses/return_loss.py
monk/gluon/models/__init__.py
monk/gluon/models/common.py
monk/gluon/models/features.py
monk/gluon/models/imports.py
monk/gluon/models/initializers.py
monk/gluon/models/layers.py
monk/gluon/models/models.py
monk/gluon/models/params.py
monk/gluon/models/return_model.py
monk/gluon/optimizers/__init__.py
monk/gluon/optimizers/imports.py
monk/gluon/optimizers/optimizers.py
monk/gluon/optimizers/retrieve_optimizer.py
monk/gluon/optimizers/return_optimizer.py
monk/gluon/schedulers/__init__.py
monk/gluon/schedulers/imports.py
monk/gluon/schedulers/retrieve_scheduler.py
monk/gluon/schedulers/return_scheduler.py
monk/gluon/schedulers/schedulers.py
monk/gluon/testing/__init__.py
monk/gluon/testing/imports.py
monk/gluon/testing/process.py
monk_keras_cuda102_test-0.0.1.dist-info/LICENSE.md
monk_keras_cuda102_test-0.0.1.dist-info/METADATA
monk_keras_cuda102_test-0.0.1.dist-info/WHEEL
monk_keras_cuda102_test-0.0.1.dist-info/top_level.txt
monk_keras_cuda102_test-0.0.1.dist-info/RECORD
